{
    "swagger": "2.0",
    "info": {
        "description": "defaultDescription",
        "version": "0.2",
        "title": "defaultTitle"
    },
    "paths": {
        "/products": {
            "post": {
                "consumes": ["application/json"],
                "produces": ["application/json"],
                "parameters": [{
                    "in": "body",
                    "name": "body",
                    "required": false,
                    "schema": {
                        "$ref": "#/definitions/Model3"
                    },
                    "x-examples": {
                        "application/json": "{\n\t   \"name\": \"amany\",\n        \"display_name\": \"reco\",\n        \"description\": \".description\",\n        \"category\":\"sport\"\n}"
                    }
                }, {
                    "name": "param0",
                    "in": "path",
                    "description": "Example values form path are: 'products' and 'categories'",
                    "required": true,
                    "type": "string"
                }],
                "responses": {
                    "200": {
                        "description": "Definition generated from Swagger Inspector",
                        "schema": {
                            "$ref": "#/definitions/Model6"
                        }
                    }
                }
            }
        },
        "/products/": {
            "get": {
                "produces": ["application/json"],
                "parameters": [{
                    "name": "param1",
                    "in": "path",
                    "description": "Example values form path are: 'products' and 'categories'",
                    "required": true,
                    "type": "string"
                }],
                "responses": {
                    "200": {
                        "description": "Definition generated from Swagger Inspector",
                        "schema": {
                            "$ref": "#/definitions/Model7"
                        }
                    }
                }
            }
        },
        "/products/1": {
            "get": {
                "produces": ["application/json"],
                "parameters": [{
                    "name": "param2",
                    "in": "path",
                    "description": "Example values form path are: 'products' and 'categories'",
                    "required": true,
                    "type": "string"
                }, {
                    "name": "param3",
                    "in": "path",
                    "description": "Example values form path are: '1' and '2'",
                    "required": true,
                    "type": "string"
                }],
                "responses": {
                    "200": {
                        "description": "Definition generated from Swagger Inspector",
                        "schema": {
                            "$ref": "#/definitions/Model8"
                        }
                    }
                }
            }
        },
        "/products/1/": {
            "put": {
                "consumes": ["application/json"],
                "produces": ["application/json"],
                "parameters": [{
                    "in": "body",
                    "name": "body",
                    "required": false,
                    "schema": {
                        "$ref": "#/definitions/Model0"
                    },
                    "x-examples": {
                        "application/json": "{\n\t   \"name\": \"ammar\",\n        \"display_name\": \"ammar product\",\n        \"description\": \".description\",\n        \"category\":\"sport\"\n}"
                    }
                }, {
                    "name": "param4",
                    "in": "path",
                    "description": "Example values form path are: 'products' and 'categories'",
                    "required": true,
                    "type": "string"
                }, {
                    "name": "param5",
                    "in": "path",
                    "description": "Example values form path are: '1' and '2'",
                    "required": true,
                    "type": "string"
                }],
                "responses": {
                    "200": {
                        "description": "Definition generated from Swagger Inspector",
                        "schema": {
                            "$ref": "#/definitions/Model9"
                        }
                    }
                }
            }
        },
        "/products/2": {
            "delete": {
                "consumes": ["application/json"],
                "produces": ["application/json"],
                "parameters": [{
                    "in": "body",
                    "name": "body",
                    "required": false,
                    "schema": {
                        "$ref": "#/definitions/Model1"
                    },
                    "x-examples": {
                        "application/json": "{\n\t   \"name\": \"ammar\",\n        \"display_name\": \"ammar product\",\n        \"description\": \".description\",\n        \"category\":\"sport\"\n}"
                    }
                }, {
                    "name": "param6",
                    "in": "path",
                    "description": "Example values form path are: 'products' and 'categories'",
                    "required": true,
                    "type": "string"
                }],
                "responses": {
                    "200": {
                        "description": "Definition generated from Swagger Inspector",
                        "schema": {
                            "$ref": "#/definitions/Model10"
                        }
                    }
                }
            }
        }
    },
    "definitions": {
        "Model0": {
            "properties": {
                "name": {
                    "type": "string"
                },
                "display_name": {
                    "type": "string"
                },
                "description": {
                    "type": "string"
                },
                "category": {
                    "type": "string"
                }
            }
        },
        "Model1": {
            "properties": {
                "name": {
                    "type": "string"
                },
                "display_name": {
                    "type": "string"
                },
                "description": {
                    "type": "string"
                },
                "category": {
                    "type": "string"
                }
            }
        },
        "Model3": {
            "properties": {
                "name": {
                    "type": "string"
                },
                "display_name": {
                    "type": "string"
                },
                "description": {
                    "type": "string"
                },
                "category": {
                    "type": "string"
                }
            }
        },
        "Model6": {
            "properties": {
                "name": {
                    "type": "string"
                },
                "display_name": {
                    "type": "string"
                },
                "description": {
                    "type": "string"
                },
                "category": {
                    "type": "string"
                },
                "id": {
                    "type": "integer",
                    "format": "int32"
                }
            }
        },
        "Array": {
            "properties": {
                "name": {
                    "type": "string"
                },
                "display_name": {
                    "type": "string"
                },
                "description": {
                    "type": "string"
                },
                "category": {
                    "type": "string"
                },
                "id": {
                    "type": "integer",
                    "format": "int32"
                }
            }
        },
        "Model7": {
            "type": "array",
            "items": {
                "$ref": "#/definitions/Array"
            }
        },
        "Model8_Array": {
            "properties": {
                "name": {
                    "type": "string"
                },
                "display_name": {
                    "type": "string"
                },
                "description": {
                    "type": "string"
                },
                "category": {
                    "type": "string"
                },
                "id": {
                    "type": "integer",
                    "format": "int32"
                }
            }
        },
        "Model8": {
            "type": "array",
            "items": {
                "$ref": "#/definitions/Model8_Array"
            }
        },
        "Model9": {
            "properties": {
                "name": {
                    "type": "string"
                },
                "display_name": {
                    "type": "string"
                },
                "description": {
                    "type": "string"
                },
                "category": {
                    "type": "string"
                },
                "id": {
                    "type": "string"
                }
            }
        },
        "Model10_Array": {
            "properties": {
                "name": {
                    "type": "string"
                },
                "display_name": {
                    "type": "string"
                },
                "description": {
                    "type": "string"
                },
                "category": {
                    "type": "string"
                },
                "id": {
                    "type": "integer",
                    "format": "int32"
                }
            }
        },
        "Model10": {
            "type": "array",
            "items": {
                "$ref": "#/definitions/Model10_Array"
            }
        },
        "Model12_Array": {
            "properties": {
                "name": {
                    "type": "string"
                },
                "display_name": {
                    "type": "string"
                },
                "description": {
                    "type": "string"
                },
                "id": {
                    "type": "integer",
                    "format": "int32"
                }
            }
        },
        "Model13_Array": {
            "properties": {
                "name": {
                    "type": "string"
                },
                "display_name": {
                    "type": "string"
                },
                "description": {
                    "type": "string"
                },
                "id": {
                    "type": "integer",
                    "format": "int32"
                }
            }
        },
        "Model15_Array": {
            "properties": {
                "name": {
                    "type": "string"
                },
                "display_name": {
                    "type": "string"
                },
                "description": {
                    "type": "string"
                },
                "id": {
                    "type": "string"
                }
            }
        }
    }
}